LICENSE
MANIFEST.in
README.rst
setup.py
apollo/__init__.py
apollo/admin.py
apollo/forms.py
apollo/models.py
apollo/tests.py
apollo/urls.py
apollo/views.py
apollo/static/apollo.js
apollo/templates/apollo/button.html
apollo/templates/apollo/button_content.html
apollo/templates/apollo/buttons.html
apollo/templates/apollo/confirm.html
apollo/templates/apollo/forms.html
apollo/templates/apollo/questions.html
django_apollo.egg-info/PKG-INFO
django_apollo.egg-info/SOURCES.txt
django_apollo.egg-info/dependency_links.txt
django_apollo.egg-info/requires.txt
django_apollo.egg-info/top_level.txt