Metadata-Version: 1.1
Name: django-apollo
Version: 0.2
Summary: A simple landing page Django app with quick setup, minimal dependencies, but still managable from Django admin pages.
Home-page: https://github.com/dbroudy/django-apollo/
Author: David Broudy
Author-email: dave@broudy.net
License: MIT
Keywords: landing page mvp minimum viable project launch
Platform: UNKNOWN
Classifier: Environment :: Web Environment
Classifier: Framework :: Django
Classifier: Intended Audience :: Developers
Classifier: License :: OSI Approved :: MIT License
Classifier: Operating System :: OS Independent
Classifier: Programming Language :: Python
Classifier: Topic :: Internet :: WWW/HTTP
Classifier: Topic :: Internet :: WWW/HTTP :: Dynamic Content
Classifier: Topic :: Software Development :: Libraries :: Python Modules
